gitberg-0.6.3.data/scripts/gitberg
gitenberg/.DS_Store
gitenberg/__init__.py
gitenberg/__init__.pyc
gitenberg/actions.py
gitenberg/actions.pyc
gitenberg/book.py
gitenberg/book.pyc
gitenberg/clone.py
gitenberg/clone.pyc
gitenberg/config.py
gitenberg/config.pyc
gitenberg/dialog.py
gitenberg/dialog.pyc
gitenberg/fetch.py
gitenberg/fetch.pyc
gitenberg/library.py
gitenberg/library.pyc
gitenberg/local_repo.py
gitenberg/local_repo.pyc
gitenberg/make.py
gitenberg/make.pyc
gitenberg/parameters.py
gitenberg/parameters.pyc
gitenberg/pg_wikipedia.py
gitenberg/pg_wikipedia.pyc
gitenberg/push.py
gitenberg/push.pyc
gitenberg/workflow.py
gitenberg/workflow.pyc
gitenberg/data/.DS_Store
gitenberg/data/GITenberg_repo_list.tsv
gitenberg/data/gutenberg_descriptions.json
gitenberg/data/missing.tsv
gitenberg/gitenberg/__init__.py
gitenberg/gitenberg/__init__.pyc
gitenberg/metadata/.DS_Store
gitenberg/metadata/__init__.py
gitenberg/metadata/__init__.pyc
gitenberg/metadata/fileinfo.py
gitenberg/metadata/fileinfo.pyc
gitenberg/metadata/licenses.py
gitenberg/metadata/licenses.pyc
gitenberg/metadata/marc.py
gitenberg/metadata/marc.pyc
gitenberg/metadata/pandata.py
gitenberg/metadata/pandata.pyc
gitenberg/metadata/parameters.py
gitenberg/metadata/parameters.pyc
gitenberg/metadata/pg_rdf.py
gitenberg/metadata/pg_rdf.pyc
gitenberg/metadata/utils.py
gitenberg/metadata/utils.pyc
gitenberg/templates/.DS_Store
gitenberg/templates/CONTRIBUTING.rst
gitenberg/templates/LICENSE
gitenberg/templates/README.rst.j2
gitenberg/tests/.DS_Store
gitenberg/tests/__init__.py
gitenberg/tests/__init__.pyc
gitenberg/tests/test_book.py
gitenberg/tests/test_book.pyc
gitenberg/tests/test_config.py
gitenberg/tests/test_config.pyc
gitenberg/tests/test_cover.py
gitenberg/tests/test_fetch.py
gitenberg/tests/test_fetch.pyc
gitenberg/tests/test_local_repo.py
gitenberg/tests/test_local_repo.pyc
gitenberg/tests/test_make.py
gitenberg/tests/test_make.pyc
gitenberg/tests/test_metadata.py
gitenberg/tests/test_metadata.pyc
gitberg-0.6.3.dist-info/LICENSE
gitberg-0.6.3.dist-info/METADATA
gitberg-0.6.3.dist-info/WHEEL
gitberg-0.6.3.dist-info/top_level.txt
gitberg-0.6.3.dist-info/RECORD
