Metadata-Version: 2.1
Name: gitberg
Version: 0.6.3
Summary: A library and command for interacting with the GITenberg books project
Home-page: https://github.com/gitenberg-dev/gitberg
Author: Seth Woodworth
Author-email: seth@sethish.com
License: GPLv3
Keywords: books ebooks gitenberg gutenberg epub metadata
Platform: UNKNOWN
Classifier: Development Status :: 3 - Alpha
Classifier: Intended Audience :: Developers
Classifier: License :: OSI Approved :: GNU General Public License (GPL)
Classifier: Programming Language :: Python :: 2.7
Requires-Dist: requests (>=2.7)
Requires-Dist: uritemplate.py (>=0.3.0)
Requires-Dist: github3.py (>=1.0.0)
Requires-Dist: GitPython (>=2.1.8)
Requires-Dist: docopt (>=0.6)
Requires-Dist: sh (>=1)
Requires-Dist: Jinja2 (>=2.7)
Requires-Dist: semver (==2.2.0)
Requires-Dist: tox (>=2.5.0)
Requires-Dist: appdirs (==1.4.0)
Requires-Dist: beautifulsoup4 (>=4.6.0)
Requires-Dist: wikipedia (==1.4.0)
Requires-Dist: six (>=1.10.0)
Requires-Dist: pymarc (==3.0.3)
Requires-Dist: PyYAML (>=3.13)
Requires-Dist: SPARQLWrapper (==1.6.4)
Requires-Dist: html5lib (==1.0.1)
Requires-Dist: isodate (==0.6.0)
Requires-Dist: pytz (>=2016.6.1)
Requires-Dist: pyparsing (>=2.3.0)
Requires-Dist: rdflib (==4.2.2)
Requires-Dist: rdflib-jsonld (==0.4.0)
Requires-Dist: mock (==2.0.0)
Requires-Dist: cffi (>=1.9.1)
Requires-Dist: cairocffi (==0.8.0)
Requires-Dist: pycparser (>=2.17)
Requires-Dist: cryptography (>=1.7.2)
Requires-Dist: pyepub (==0.3.2)
Requires-Dist: python-dateutil (>=2.6.0)
Requires-Dist: pyasn1 (>=0.4.2)
Requires-Dist: pyOpenSSL (>=0.13)
Requires-Dist: certifi (>=2017.4.17)
Requires-Dist: cryptography (>=2.1.4)
